meshtools/__init__.py
meshtools/obj.py
meshtools-0.2.0.dist-info/LICENSE
meshtools-0.2.0.dist-info/METADATA
meshtools-0.2.0.dist-info/WHEEL
meshtools-0.2.0.dist-info/top_level.txt
meshtools-0.2.0.dist-info/RECORD
